CVHealthEva/__init__.py
CVHealthEva/kernels.py
CVHealthEva-1.0.5.dist-info/METADATA
CVHealthEva-1.0.5.dist-info/WHEEL
CVHealthEva-1.0.5.dist-info/top_level.txt
CVHealthEva-1.0.5.dist-info/RECORD
