Metadata-Version: 2.1
Name: CVHealthEva
Version: 1.0.5
Summary: CVD score & CVD age
Home-page: https://github.com/VVictorChen/CVHealthEva
Author: Victor
Author-email: chenweibang@genomics.cn
License: UNKNOWN
Platform: UNKNOWN
Classifier: Programming Language :: Python :: 3
Classifier: License :: OSI Approved :: MIT License
Classifier: Operating System :: OS Independent
Requires-Python: >=3.6
